rio_diff/__init__.py
rio_diff/compare.py
rio_diff/scripts/__init__.py
rio_diff/scripts/cli.py
rio_diff-1.0.dev1.dist-info/METADATA
rio_diff-1.0.dev1.dist-info/WHEEL
rio_diff-1.0.dev1.dist-info/entry_points.txt
rio_diff-1.0.dev1.dist-info/licenses/LICENSE
rio_diff-1.0.dev1.dist-info/RECORD
