Metadata-Version: 2.4
Name: rio-diff
Version: 1.0.dev1
Summary: Raster comparison plugin for rasterio
Project-URL: Homepage, https://github.com/perminovsi/rio-diff
Author-email: Sergey Perminov <perminovsi@ya.ru>
License-Expression: MIT
License-File: LICENSE
Keywords: raster,rasterio,rio-plugin
Classifier: Intended Audience :: Information Technology
Classifier: Intended Audience :: Science/Research
Classifier: Programming Language :: Python :: 3
Classifier: Topic :: Scientific/Engineering :: GIS
Requires-Python: >=3.11
Requires-Dist: click>=7.0
Requires-Dist: numpy>=2.0
Requires-Dist: rasterio>=1.3
